pytest_gcs/__init__.py
pytest_gcs/config.py
pytest_gcs/plugin.py
pytest_gcs/py.typed
pytest_gcs/executor/__init__.py
pytest_gcs/executor/process.py
pytest_gcs/factories/__init__.py
pytest_gcs/factories/client.py
pytest_gcs/factories/proc.py
pytest_gcs-0.1.0.dist-info/LICENSE
pytest_gcs-0.1.0.dist-info/METADATA
pytest_gcs-0.1.0.dist-info/WHEEL
pytest_gcs-0.1.0.dist-info/entry_points.txt
pytest_gcs-0.1.0.dist-info/top_level.txt
pytest_gcs-0.1.0.dist-info/RECORD
