Metadata-Version: 2.2
Name: pytest-gcs
Version: 0.1.0
Summary: GCS fixtures and fixture factories for Pytest.
Author-email: Sam Pegler <sam@sampegler.co.uk>
License: Copyright (c) 2024 Sam Pegler
Project-URL: Source, https://github.com/Poogles/pytest-gcs
Project-URL: Bug Tracker, https://github.com/Poogles/pytest-gcs/issues
Keywords: tests,pytest,fixture,gcs
Classifier: Development Status :: 5 - Production/Stable
Classifier: Environment :: Web Environment
Classifier: Intended Audience :: Developers
Classifier: License :: OSI Approved :: GNU Lesser General Public License v3 or later (LGPLv3+)
Classifier: Natural Language :: English
Classifier: Operating System :: OS Independent
Classifier: Programming Language :: Python
Classifier: Programming Language :: Python :: 3
Classifier: Programming Language :: Python :: 3.8
Classifier: Programming Language :: Python :: 3.9
Classifier: Programming Language :: Python :: 3.10
Classifier: Programming Language :: Python :: 3.11
Classifier: Programming Language :: Python :: 3 :: Only
Classifier: Topic :: Software Development :: Libraries :: Python Modules
Classifier: Topic :: Software Development :: Testing
Classifier: Framework :: Pytest
Requires-Python: >=3.8
License-File: LICENSE
Requires-Dist: pytest>=6.2
Requires-Dist: google-cloud-storage
Requires-Dist: mirakuru
Requires-Dist: port-for
Provides-Extra: test
Requires-Dist: mypy; extra == "test"
Requires-Dist: pytest-cov; extra == "test"
Requires-Dist: pydocstyle; extra == "test"
Requires-Dist: isort; extra == "test"
